{"format":2,"version":"5.5","globals":"09ebd2a981eb5edac1d23ffe30455923","files":{"application___init___py":{"hash":"c98822916422b2d2309b9250037b89b0","index":{"nums":[1,7,0,0,0,0,0],"html_filename":"application___init___py.html","relative_filename":"application\\__init__.py"}},"application_forms_py":{"hash":"71c4bab335bf2bb1fc84536033701b99","index":{"nums":[1,14,0,0,0,0,0],"html_filename":"application_forms_py.html","relative_filename":"application\\forms.py"}},"application_models_py":{"hash":"6496a73d5301f052218b17f276a35d9f","index":{"nums":[1,12,0,0,0,0,0],"html_filename":"application_models_py.html","relative_filename":"application\\models.py"}},"application_routes_py":{"hash":"97b3cb49581d81d32c72bdb727b23577","index":{"nums":[1,51,0,0,0,0,0],"html_filename":"application_routes_py.html","relative_filename":"application\\routes.py"}}}}